flaskdocs/__init__.py
flaskdocs/schema.py
flaskdocs/test_schema.py
flaskdocs-0.0.1.dist-info/METADATA
flaskdocs-0.0.1.dist-info/WHEEL
flaskdocs-0.0.1.dist-info/top_level.txt
flaskdocs-0.0.1.dist-info/RECORD
