Metadata-Version: 2.1
Name: flaskdocs
Version: 0.0.1
Summary: A packed to help generate documentation automatically for flask endpoints.
Home-page: https://github.com/mrincredibuell/flaskdocs
Author: Joseph L Buell V
Author-email: jlrbuellv@gmail.com
License: UNKNOWN
Platform: UNKNOWN
Classifier: Programming Language :: Python :: 3
Classifier: License :: OSI Approved :: MIT License
Classifier: Operating System :: OS Independent
Classifier: Development Status :: 3 - Alpha
Requires-Dist: Flask
Requires-Dist: schema
